spacial_boxcounting/__init__.py
spacial_boxcounting/_version.py
spacial_boxcounting/api.py
spacial_boxcounting/batch.py
spacial_boxcounting/cli.py
spacial_boxcounting/core.py
spacial_boxcounting/hilbert.py
spacial_boxcounting/io.py
spacial_boxcounting/utils.py
spacial_boxcounting/visualize.py
spacial_boxcounting-0.1.0.dist-info/licenses/LICENSE.txt
spacial_boxcounting-0.1.0.dist-info/METADATA
spacial_boxcounting-0.1.0.dist-info/WHEEL
spacial_boxcounting-0.1.0.dist-info/entry_points.txt
spacial_boxcounting-0.1.0.dist-info/top_level.txt
spacial_boxcounting-0.1.0.dist-info/RECORD
