Metadata-Version: 2.4
Name: spacial_boxcounting
Version: 0.1.0
Summary: Convenient package for spatial box counting and fractal analysis across data types with CPU and GPU support
Home-page: https://github.com/yourusername/spacial-boxcounting-cpu-gpu
Author: Your Name
Author-email: Your Name <your.email@example.com>
Maintainer-email: Your Name <your.email@example.com>
License-Expression: MIT
Project-URL: Homepage, https://github.com/yourusername/spacial-boxcounting-cpu-gpu
Project-URL: Repository, https://github.com/yourusername/spacial-boxcounting-cpu-gpu
Project-URL: Documentation, https://github.com/yourusername/spacial-boxcounting-cpu-gpu#readme
Project-URL: Bug Reports, https://github.com/yourusername/spacial-boxcounting-cpu-gpu/issues
Project-URL: Source Code, https://github.com/yourusername/spacial-boxcounting-cpu-gpu
Keywords: fractal-analysis,box-counting,image-processing,spatial-analysis,gpu-acceleration
Classifier: Development Status :: 3 - Alpha
Classifier: Intended Audience :: Science/Research
Classifier: Intended Audience :: Developers
Classifier: Operating System :: OS Independent
Classifier: Programming Language :: Python :: 3
Classifier: Programming Language :: Python :: 3.8
Classifier: Programming Language :: Python :: 3.9
Classifier: Programming Language :: Python :: 3.10
Classifier: Programming Language :: Python :: 3.11
Classifier: Programming Language :: Python :: 3.12
Classifier: Topic :: Scientific/Engineering :: Image Processing
Classifier: Topic :: Scientific/Engineering :: Mathematics
Requires-Python: >=3.8
License-File: LICENSE.txt
Requires-Dist: numpy>=1.20.0
Requires-Dist: numba>=0.53.0
Requires-Dist: Pillow>=8.0.0
Requires-Dist: matplotlib>=3.3.0
Requires-Dist: hilbertcurve>=1.0.0
Requires-Dist: pandas>=1.3.0
Provides-Extra: gpu
Requires-Dist: cupy-cuda12x>=9.0.0; extra == "gpu"
Provides-Extra: dev
Requires-Dist: pytest>=6.0.0; extra == "dev"
Requires-Dist: sphinx>=4.0.0; extra == "dev"
Requires-Dist: bandit>=1.7.0; extra == "dev"
Requires-Dist: safety>=3.0.0; extra == "dev"
Dynamic: author
Dynamic: home-page
Dynamic: license-file
Dynamic: requires-python
